pymortem/__init__.py
pymortem/core.py
pymortem-1.0.1.dist-info/licenses/LICENSE
tests/__init__.py
tests/conftest.py
tests/test_advanced.py
tests/test_core_functions.py
tests/test_exception_handling.py
tests/test_integration.py
pymortem-1.0.1.dist-info/METADATA
pymortem-1.0.1.dist-info/WHEEL
pymortem-1.0.1.dist-info/top_level.txt
pymortem-1.0.1.dist-info/RECORD
