Metadata-Version: 2.4
Name: pymortem
Version: 1.0.1
Summary: Post-mortem debugging tools for Python
Home-page: https://github.com/nsarang/pymortem
Author: Nima Sarang
Author-email: contact@nimasarang.com
Project-URL: Homepage, https://github.com/nsarang/pymortem
Project-URL: Issues, https://github.com/nsarang/pymortem/issues
Project-URL: Documentation, https://github.com/nsarang/pymortem#readme
Keywords: debugging,post-mortem,traceback,exception,development
Classifier: Development Status :: 5 - Production/Stable
Classifier: Intended Audience :: Developers
Classifier: License :: OSI Approved :: MIT License
Classifier: Programming Language :: Python :: 3
Classifier: Programming Language :: Python :: 3.9
Classifier: Programming Language :: Python :: 3.10
Classifier: Programming Language :: Python :: 3.11
Classifier: Programming Language :: Python :: 3.12
Classifier: Programming Language :: Python :: 3.13
Classifier: Topic :: Software Development :: Debuggers
Requires-Python: >=3.7
License-File: LICENSE
Dynamic: author
Dynamic: author-email
Dynamic: classifier
Dynamic: description
Dynamic: description-content-type
Dynamic: home-page
Dynamic: keywords
Dynamic: license-file
Dynamic: project-url
Dynamic: requires-python
Dynamic: summary
